please_do_not_define/__init__.py
please_do_not_define/__main__.py
please_do_not_define/__version__.py
please_do_not_define/all_name.py
please_do_not_define/invalid_name.py
please_do_not_define-0.3.6.dist-info/METADATA
please_do_not_define-0.3.6.dist-info/WHEEL
please_do_not_define-0.3.6.dist-info/entry_points.txt
please_do_not_define-0.3.6.dist-info/top_level.txt
please_do_not_define-0.3.6.dist-info/RECORD
