Metadata-Version: 2.4
Name: please_do_not_define
Version: 0.3.6
Summary: A Python library that prevents defining female-related names in code
Home-page: https://github.com/Locked-chess-official/please_do_not_define
Author: HuangHaoHua
Author-email: 13140752715@163.com
License: MIT
Project-URL: Source, https://github.com/Locked-chess-official/please_do_not_define
Project-URL: Bug Reports, https://github.com/Locked-chess-official/please_do_not_define/issues
Keywords: naming-conventions code-quality gender-neutral
Classifier: Development Status :: 3 - Alpha
Classifier: Intended Audience :: Developers
Classifier: License :: OSI Approved :: MIT License
Classifier: Programming Language :: Python :: 3
Classifier: Programming Language :: Python :: 3.7
Classifier: Programming Language :: Python :: 3.8
Classifier: Programming Language :: Python :: 3.9
Classifier: Programming Language :: Python :: 3.10
Classifier: Programming Language :: Python :: 3.11
Classifier: Programming Language :: Python :: 3.12
Classifier: Programming Language :: Python :: 3.13
Classifier: Operating System :: OS Independent
Classifier: Topic :: Software Development :: Quality Assurance
Classifier: Topic :: Software Development :: Libraries :: Python Modules
Requires-Python: >=3.7
Dynamic: author
Dynamic: author-email
Dynamic: classifier
Dynamic: description
Dynamic: description-content-type
Dynamic: home-page
Dynamic: keywords
Dynamic: license
Dynamic: project-url
Dynamic: requires-python
Dynamic: summary
